{
  "flight": "2026-06-25_66km",
  "source_file": "examples\\data\\igc\\2026-06-25_66km.igc",
  "n_fixes": 7600,
  "altitude_source": "gnss",
  "calibration": {
    "offset_m": -3.7976187615302024,
    "method": "ground_landing",
    "confidence": "medium",
    "n_ground": 22,
    "offset_start": null,
    "offset_end": -3.7976187615302024,
    "iqr_m": 0.25820517170927815,
    "note": "Nur Lande-Bodensegment verwendet (luftiger Start?).",
    "takeoff_t_s": 0.0,
    "landing_t_s": 7593.0
  },
  "n_events": 34,
  "resolution_m": 0.5,
  "n_inflight": 7455,
  "min_d3_terrain_inflight_m": 22.4,
  "min_d3_surface_inflight_m": 15.3,
  "dtm_tiles": {
    "2612-1158": 2025,
    "2612-1159": 2025,
    "2612-1160": 2025,
    "2612-1161": 2025,
    "2613-1158": 2025,
    "2613-1159": 2025,
    "2613-1160": 2025,
    "2613-1161": 2025,
    "2614-1158": 2025,
    "2614-1159": 2025,
    "2614-1160": 2025,
    "2614-1161": 2025,
    "2615-1158": 2025,
    "2615-1159": 2025,
    "2615-1160": 2025,
    "2615-1161": 2025,
    "2616-1158": 2025,
    "2616-1159": 2025,
    "2616-1160": 2025,
    "2616-1161": 2025
  },
  "dsm_tiles": {
    "2612-1158": 2022,
    "2612-1159": 2022,
    "2612-1160": 2022,
    "2612-1161": 2022,
    "2613-1158": 2022,
    "2613-1159": 2022,
    "2613-1160": 2022,
    "2613-1161": 2022,
    "2614-1158": 2022,
    "2614-1159": 2022,
    "2614-1160": 2022,
    "2614-1161": 2022,
    "2615-1158": 2022,
    "2615-1159": 2022,
    "2615-1160": 2022,
    "2615-1161": 2022,
    "2616-1158": 2022,
    "2616-1159": 2022,
    "2616-1160": 2022,
    "2616-1161": 2022
  },
  "transform_pipeline": "axis order change (2D) + Inverse of CH1903+ to WGS 84 (1) + Swiss Oblique Mercator 1995",
  "r_cap_m": 300.0,
  "uncertainty": {
    "sigma_h_m": 3.0,
    "sigma_v_m": 5.0,
    "n_samples": 80,
    "calib_iqr_m": 0.25820517170927815
  }
}